data_quality_checks-0.0.1.dist-info/licenses/LICENSE
dq_engine/__init__.py
dq_engine/run_dq_engine.py
data_quality_checks-0.0.1.dist-info/METADATA
data_quality_checks-0.0.1.dist-info/WHEEL
data_quality_checks-0.0.1.dist-info/top_level.txt
data_quality_checks-0.0.1.dist-info/RECORD
